partition_sknetwork/__init__.py
partition_sknetwork/partition_sknetwork.py
partition_sknetwork-0.0.3.dist-info/licenses/LICENSE
partition_sknetwork-0.0.3.dist-info/METADATA
partition_sknetwork-0.0.3.dist-info/WHEEL
partition_sknetwork-0.0.3.dist-info/top_level.txt
partition_sknetwork-0.0.3.dist-info/RECORD
