Metadata-Version: 2.4
Name: partition_sknetwork
Version: 0.0.3
Summary: Ensemble Clustering for Graphs (ECG) and Graph aware measurse (GAM) for sknetwork.
Author-email: Ryan DeWolfe <ryandewolfe33@gmail.com>
License-Expression: MIT
Project-URL: Homepage, https://github.com/ftheberge/graph-partition-and-measures
Project-URL: Issues, https://github.com/ftheberge/graph-partition-and-measures/issues
Classifier: Programming Language :: Python :: 3
Classifier: Operating System :: OS Independent
Requires-Python: >=3.10
License-File: LICENSE
Requires-Dist: numpy>=2.0
Requires-Dist: scikit-network>=0.33
Requires-Dist: numba>=0.60.0
Dynamic: license-file
